[
  {
    "inputs": [{"internalType": "address", "name": "target", "type": "address"}],
    "name": "AddressEmptyCode",
    "type": "error"
  },
  {
    "inputs": [{"internalType": "address", "name": "account", "type": "address"}],
    "name": "AddressInsufficientBalance",
    "type": "error"
  },
  {"inputs": [], "name": "FailedInnerCall", "type": "error"},
  {"inputs": [], "name": "MathOverflowedMulDiv", "type": "error"},
  {
    "inputs": [{"internalType": "address", "name": "token", "type": "address"}],
    "name": "SafeERC20FailedOperation",
    "type": "error"
  },
  {
    "anonymous": false,
    "inputs": [
      {"indexed": false, "internalType": "uint256", "name": "_out", "type": "uint256"},
      {"indexed": false, "internalType": "uint256", "name": "_in", "type": "uint256"}
    ],
    "name": "Pop",
    "type": "event"
  },
  {
    "anonymous": false,
    "inputs": [
      {"indexed": false, "internalType": "uint256", "name": "_in", "type": "uint256"},
      {"indexed": false, "internalType": "uint256", "name": "_out", "type": "uint256"}
    ],
    "name": "Put",
    "type": "event"
  },
  {
    "anonymous": false,
    "inputs": [
      {"indexed": false, "internalType": "address", "name": "from", "type": "address"},
      {
        "components": [
          {"internalType": "address", "name": "next", "type": "address"},
          {"internalType": "address", "name": "prev", "type": "address"},
          {"internalType": "address", "name": "asset", "type": "address"},
          {"internalType": "uint256", "name": "stake", "type": "uint256"},
          {"internalType": "uint256", "name": "debt", "type": "uint256"},
          {"internalType": "uint256", "name": "end", "type": "uint256"}
        ],
        "indexed": false,
        "internalType": "struct UAHT_JAR.Position",
        "name": "position",
        "type": "tuple"
      }
    ],
    "name": "Sync",
    "type": "event"
  },
  {
    "inputs": [],
    "name": "base",
    "outputs": [{"internalType": "address", "name": "", "type": "address"}],
    "stateMutability": "view",
    "type": "function"
  },
  {
    "inputs": [{"internalType": "address", "name": "asset", "type": "address"}],
    "name": "free_asset",
    "outputs": [{"internalType": "uint256", "name": "", "type": "uint256"}],
    "stateMutability": "view",
    "type": "function"
  },
  {
    "inputs": [],
    "name": "free_uaht",
    "outputs": [{"internalType": "uint256", "name": "", "type": "uint256"}],
    "stateMutability": "view",
    "type": "function"
  },
  {
    "inputs": [],
    "name": "jar",
    "outputs": [{"internalType": "address", "name": "", "type": "address"}],
    "stateMutability": "view",
    "type": "function"
  },
  {
    "inputs": [],
    "name": "max_uaht",
    "outputs": [{"internalType": "uint256", "name": "", "type": "uint256"}],
    "stateMutability": "view",
    "type": "function"
  },
  {
    "inputs": [
      {"internalType": "address", "name": "asset", "type": "address"},
      {"internalType": "uint256", "name": "uaht", "type": "uint256"},
      {"internalType": "address", "name": "to", "type": "address"}
    ],
    "name": "pop",
    "outputs": [{"internalType": "uint256", "name": "", "type": "uint256"}],
    "stateMutability": "nonpayable",
    "type": "function"
  },
  {
    "inputs": [{"internalType": "address", "name": "", "type": "address"}],
    "name": "position",
    "outputs": [
      {"internalType": "address", "name": "next", "type": "address"},
      {"internalType": "address", "name": "prev", "type": "address"},
      {"internalType": "address", "name": "asset", "type": "address"},
      {"internalType": "uint256", "name": "stake", "type": "uint256"},
      {"internalType": "uint256", "name": "debt", "type": "uint256"},
      {"internalType": "uint256", "name": "end", "type": "uint256"}
    ],
    "stateMutability": "view",
    "type": "function"
  },
  {
    "inputs": [
      {"internalType": "address", "name": "asset", "type": "address"},
      {"internalType": "uint256", "name": "amount", "type": "uint256"},
      {"internalType": "uint256", "name": "_days", "type": "uint256"}
    ],
    "name": "put",
    "outputs": [{"internalType": "uint256", "name": "", "type": "uint256"}],
    "stateMutability": "nonpayable",
    "type": "function"
  },
  {
    "inputs": [{"internalType": "address", "name": "asset", "type": "address"}],
    "name": "simulate_free_asset",
    "outputs": [{"internalType": "uint256", "name": "", "type": "uint256"}],
    "stateMutability": "nonpayable",
    "type": "function"
  },
  {
    "inputs": [{"internalType": "address", "name": "", "type": "address"}],
    "name": "stake",
    "outputs": [{"internalType": "uint256", "name": "", "type": "uint256"}],
    "stateMutability": "view",
    "type": "function"
  },
  {
    "inputs": [],
    "name": "sync",
    "outputs": [],
    "stateMutability": "nonpayable",
    "type": "function"
  },
  {
    "inputs": [{"internalType": "address", "name": "index", "type": "address"}],
    "name": "sync_position",
    "outputs": [],
    "stateMutability": "nonpayable",
    "type": "function"
  },
  {
    "inputs": [
      {"internalType": "address", "name": "asset", "type": "address"},
      {"internalType": "uint256", "name": "uaht", "type": "uint256"}
    ],
    "name": "to_asset",
    "outputs": [{"internalType": "uint256", "name": "", "type": "uint256"}],
    "stateMutability": "view",
    "type": "function"
  },
  {
    "inputs": [
      {"internalType": "address", "name": "asset", "type": "address"},
      {"internalType": "uint256", "name": "amount", "type": "uint256"},
      {"internalType": "uint256", "name": "_days", "type": "uint256"}
    ],
    "name": "to_uaht",
    "outputs": [{"internalType": "uint256", "name": "", "type": "uint256"}],
    "stateMutability": "view",
    "type": "function"
  },
  {
    "inputs": [{"internalType": "address", "name": "asset", "type": "address"}],
    "name": "total_asset",
    "outputs": [{"internalType": "uint256", "name": "", "type": "uint256"}],
    "stateMutability": "view",
    "type": "function"
  },
  {
    "inputs": [],
    "name": "total_uaht",
    "outputs": [{"internalType": "uint256", "name": "", "type": "uint256"}],
    "stateMutability": "view",
    "type": "function"
  },
  {
    "inputs": [],
    "name": "uaht_dao",
    "outputs": [{"internalType": "address", "name": "", "type": "address"}],
    "stateMutability": "view",
    "type": "function"
  },
  {
    "inputs": [],
    "name": "uaht_oracle",
    "outputs": [{"internalType": "address", "name": "", "type": "address"}],
    "stateMutability": "view",
    "type": "function"
  },
  {
    "inputs": [{"internalType": "address", "name": "asset", "type": "address"}],
    "name": "value",
    "outputs": [{"internalType": "uint256", "name": "", "type": "uint256"}],
    "stateMutability": "view",
    "type": "function"
  }
]
